Metadata-Version: 2.1
Name: Image-AutoTrainer
Version: 1.5.0
Summary: It's an auto image classification library
Home-page: https://github.com/yinsights8/Image_AutoTrainer
Author: Yash Dhakade
Author-email: yinsights8@gmail.com
License: MIT
Keywords: autotrainer
Classifier: Development Status :: 3 - Alpha
Classifier: Intended Audience :: Developers
Classifier: Topic :: Software Development :: Build Tools
Classifier: License :: OSI Approved :: MIT License
Classifier: Programming Language :: Python :: 3.8
Classifier: Programming Language :: Python :: 3.9
Classifier: Programming Language :: Python :: 3.10
Classifier: Programming Language :: Python :: 3.11
Classifier: Programming Language :: Python :: 3.12
License-File: LICENSE
